{
	"IcoMoonType": "selection",
	"icons": [
		{
			"icon": {
				"paths": [
					"M792.73 425.626c-20.838 21.402-240.384 230.554-240.384 230.554-11.162 11.418-25.754 17.101-40.346 17.101-14.643 0-29.235-5.683-40.346-17.101 0 0-219.546-209.152-240.435-230.554-20.838-21.402-22.272-59.853 0-82.739 22.323-22.835 53.402-24.627 80.691 0l200.090 191.898 200.038-191.846c27.341-24.627 58.47-22.835 80.691 0 22.323 22.835 20.941 61.338 0 82.688z"
				],
				"attrs": [
					{}
				],
				"defaultCode": 58880,
				"grid": 0
			},
			"attrs": [
				{}
			],
			"properties": {
				"id": 0,
				"order": 5,
				"prevSize": 32,
				"code": 58880,
				"name": "uniE600",
				"ligatures": ""
			},
			"setIdx": 0,
			"iconIdx": 0
		},
		{
			"icon": {
				"paths": [
					"M792.73 572.774c-20.838-21.402-240.384-230.502-240.384-230.502-11.162-11.418-25.754-17.152-40.346-17.152-14.643 0-29.235 5.734-40.346 17.152 0 0-219.546 209.101-240.435 230.502-20.838 21.402-22.272 59.904 0 82.739 22.323 22.784 53.402 24.627 80.691 0l200.090-191.846 200.038 191.846c27.341 24.627 58.47 22.784 80.691 0 22.323-22.886 20.941-61.389 0-82.739z"
				],
				"attrs": [
					{}
				],
				"defaultCode": 58881,
				"grid": 0
			},
			"attrs": [
				{}
			],
			"properties": {
				"id": 1,
				"order": 6,
				"prevSize": 32,
				"code": 58881,
				"name": "uniE601",
				"ligatures": ""
			},
			"setIdx": 0,
			"iconIdx": 1
		},
		{
			"icon": {
				"paths": [
					"M0 0v1024h1024v-1024h-1024zM960 960h-896v-896h896v896zM768 224l-320 320-192-192-128 128 320 320 448-448-128-128z"
				],
				"tags": [
					"checkbox-checked",
					"tick",
					"checked",
					"selected"
				],
				"grid": 16
			},
			"properties": {
				"id": 312,
				"order": 7,
				"prevSize": 32,
				"code": 58882,
				"name": "checkbox-checked",
				"ligatures": ""
			},
			"setIdx": 4,
			"iconIdx": 312
		},
		{
			"icon": {
				"paths": [
					"M0 0v1024h1024v-1024h-1024zM960 960h-896v-896h896v896z"
				],
				"tags": [
					"checkbox-unchecked",
					"unchecked",
					"square"
				],
				"grid": 16
			},
			"properties": {
				"id": 313,
				"order": 8,
				"prevSize": 32,
				"code": 58883,
				"name": "checkbox-unchecked",
				"ligatures": ""
			},
			"setIdx": 4,
			"iconIdx": 313
		},
		{
			"icon": {
				"paths": [
					"M512 0c-282.77 0-512 229.23-512 512s229.23 512 512 512 512-229.23 512-512-229.23-512-512-512zM512 896c-212.078 0-384-171.922-384-384s171.922-384 384-384c212.078 0 384 171.922 384 384 0 212.078-171.922 384-384 384zM320 512c0-106.039 85.961-192 192-192 106.039 0 192 85.961 192 192 0 106.039-85.961 192-192 192-106.039 0-192-85.961-192-192z"
				],
				"tags": [
					"radio-checked"
				],
				"grid": 16
			},
			"properties": {
				"id": 315,
				"order": 9,
				"prevSize": 32,
				"code": 58884,
				"name": "radio-checked",
				"ligatures": ""
			},
			"setIdx": 4,
			"iconIdx": 315
		},
		{
			"icon": {
				"paths": [
					"M512 0c-282.77 0-512 229.23-512 512s229.23 512 512 512 512-229.23 512-512-229.23-512-512-512zM512 896c-212.078 0-384-171.922-384-384s171.922-384 384-384c212.078 0 384 171.922 384 384 0 212.078-171.922 384-384 384z"
				],
				"tags": [
					"radio-unchecked",
					"circle"
				],
				"grid": 16
			},
			"properties": {
				"id": 316,
				"order": 10,
				"prevSize": 32,
				"code": 58885,
				"name": "radio-unchecked",
				"ligatures": ""
			},
			"setIdx": 4,
			"iconIdx": 316
		}
	],
	"height": 1024,
	"metadata": {
		"name": "icomoon"
	},
	"preferences": {
		"showGlyphs": true,
		"showQuickUse": true,
		"fontPref": {
			"prefix": "icon-",
			"metadata": {
				"fontFamily": "icomoon"
			},
			"metrics": {
				"emSize": 512,
				"baseline": 6.25,
				"whitespace": 50
			}
		},
		"imagePref": {},
		"historySize": 100,
		"showCodes": true,
		"search": ""
	}
}